Metadata-Version: 1.0
Name: daot
Version: 0.7.4
Summary: the dao to programming, lisp meets prolog in python.
Home-page: https://github.com/chaosim/dao
Author: Cao Xingming(Simeon.Chaos)
Author-email: simeon.chaos@gmail.com
License: GPL
Download-URL: http://pypi.python.org/pypi/daot
Keywords: dao dinpy lisp prolog dsl
Platform: Posix; MacOS X; Windows
Classifier: Development Status :: 3 - Alpha
Classifier: License :: OSI Approved :: GNU General Public License (GPL)
Classifier: Natural Language :: Chinese (Simplified)
Classifier: Programming Language :: Python
Classifier: Topic :: Software Development :: Compilers
Classifier: Topic :: Text Processing :: General
Classifier: Intended Audience :: Developers
